MANIFEST.in
README.rst
requirements.txt
setup.py
passaporte_web/__init__.py
passaporte_web/main.py
passaporte_web/tests/__init__.py
passaporte_web/tests/application.py
passaporte_web/tests/helpers.py
passaporte_web/tests/history.py
passaporte_web/tests/identity.py
passaporte_web/tests/members.py
passaporte_web/tests/notification.py
passaporte_web/tests/service_account.py
passaporte_web/tests/cassettes/passaporte_web/accounts/account_options
passaporte_web/tests/cassettes/passaporte_web/accounts/application_using_invalid_credentials
passaporte_web/tests/cassettes/passaporte_web/accounts/application_without_permissions
passaporte_web/tests/cassettes/passaporte_web/accounts/create_with_expiration_after_9999
passaporte_web/tests/cassettes/passaporte_web/accounts/create_with_expiration_in_the_past
passaporte_web/tests/cassettes/passaporte_web/accounts/create_with_invalid_expiration
passaporte_web/tests/cassettes/passaporte_web/accounts/create_with_invalid_uuid
passaporte_web/tests/cassettes/passaporte_web/accounts/create_with_name
passaporte_web/tests/cassettes/passaporte_web/accounts/create_with_uuid
passaporte_web/tests/cassettes/passaporte_web/accounts/create_with_uuid_from_an_expired_account
passaporte_web/tests/cassettes/passaporte_web/accounts/create_without_name_or_uuid
passaporte_web/tests/cassettes/passaporte_web/accounts/duplicated_account
passaporte_web/tests/cassettes/passaporte_web/accounts/get
passaporte_web/tests/cassettes/passaporte_web/accounts/get_account_from_other_service
passaporte_web/tests/cassettes/passaporte_web/accounts/get_expired_account
passaporte_web/tests/cassettes/passaporte_web/accounts/history
passaporte_web/tests/cassettes/passaporte_web/accounts/load_expired_user_accounts
passaporte_web/tests/cassettes/passaporte_web/accounts/load_expired_user_accounts_from_other_services
passaporte_web/tests/cassettes/passaporte_web/accounts/load_expired_user_accounts_with_a_given_role
python_passaporte_web.egg-info/PKG-INFO
python_passaporte_web.egg-info/SOURCES.txt
python_passaporte_web.egg-info/dependency_links.txt
python_passaporte_web.egg-info/requires.txt
python_passaporte_web.egg-info/top_level.txt