Metadata-Version: 1.1
Name: python-passaporte-web
Version: 0.2.4
Summary: Python client app for Passaporte Web.
Home-page: http://github.com/myfreecomm/python-passaporte-web
Author: vitormazzi
Author-email: vitormazzi@gmail.com
License: Apache 2.0
Keywords: python passaporteweb
Platform: UNKNOWN
Classifier: Intended Audience :: Developers
Classifier: License :: OSI Approved :: Apache Software License
Classifier: Operating System :: OS Independent
Classifier: Topic :: Software Development
